README.md
setup.py
TOPSIS_Yash_101803064.egg-info/PKG-INFO
TOPSIS_Yash_101803064.egg-info/SOURCES.txt
TOPSIS_Yash_101803064.egg-info/dependency_links.txt
TOPSIS_Yash_101803064.egg-info/entry_points.txt
TOPSIS_Yash_101803064.egg-info/requires.txt
TOPSIS_Yash_101803064.egg-info/top_level.txt
Topsis_Tewatia/topsis.py