Metadata-Version: 2.1
Name: TOPSIS-Yash-101803064
Version: 1.0.1
Summary: A package -> Calculates Topsis Score and Rank them accordingly
Home-page: https://github.com/Tewatia5355/Topsis_tewatia
Author: Yash Kumar Tewatia
Author-email: yashbsr3@gmail.com
License: MIT
Platform: UNKNOWN
Classifier: Programming Language :: Python :: 3
Classifier: License :: OSI Approved :: MIT License
Classifier: Operating System :: OS Independent
